drama/__init__.py
drama/constants/__init__.py
drama/constants/constants.py
drama/geo/__init__.py
drama/geo/bistatic_pol.py
drama/geo/derived_geo.py
drama/geo/geo_history.py
drama/geo/geometry.py
drama/geo/interferometry.py
drama/geo/squinted.py
drama/geo/swath_geo.py
drama/geo/timing.py
drama/io/__init__.py
drama/io/cfg.py
drama/io/netcdf.py
drama/mission/__init__.py
drama/mission/timeline/__init__.py
drama/mission/timeline/acquisitions.py
drama/mission/timeline/formation.py
drama/mission/timeline/no_drama.py
drama/orbits/__init__.py
drama/orbits/eccentricity.py
drama/orbits/formation.py
drama/orbits/keplerian.py
drama/orbits/orbital_drifts.py
drama/orbits/repeat_design.py
drama/orbits/sunsync_orbit.py
drama/orbits/two_body.py
drama/orbits/velocity.py
drama/performance/__init__.py
drama/performance/doppler_centroid/__init__.py
drama/performance/doppler_centroid/bamler.py
drama/performance/insar/__init__.py
drama/performance/insar/snr2coh.py
drama/performance/oscillators/__init__.py
drama/performance/oscillators/phase.py
drama/performance/oscillators/phasenoisesim.py
drama/performance/sar/__init__.py
drama/performance/sar/antenna_patterns.py
drama/performance/sar/azimuth_performance.py
drama/performance/sar/data_patch.py
drama/performance/sar/mode_cfg.py
drama/performance/sar/range_ambiguities.py
drama/performance/sar/sar_performance_common.py
drama/utils/__init__.py
drama/utils/coord_trans.py
drama/utils/filtering.py
drama/utils/gohlke_transf.py
drama/utils/misc.py
drama/utils/plot.py
drama/utils/resample.py
tests/__init__.py
tests/test_geo.py
tests/test_kepler.py
drama-0.7.1.dist-info/LICENSE
drama-0.7.1.dist-info/METADATA
drama-0.7.1.dist-info/WHEEL
drama-0.7.1.dist-info/top_level.txt
drama-0.7.1.dist-info/RECORD
