Metadata-Version: 2.1
Name: drama
Version: 0.7.1
Summary: Delft Radar Modelling and perfornance Analysis (DRaMA)
Home-page: https://gitlab.tudelft.nl/drama/drama
Author: Paco López-Dekker
Author-email: F.LopezDekker@tudelft.nl
Project-URL: Bug Tracker, https://gitlab.tudelft.nl/drama/drama/-/issues
Classifier: Programming Language :: Python :: 3
Classifier: License :: OSI Approved :: GNU General Public License v3 (GPLv3)
Classifier: Operating System :: OS Independent
Classifier: Intended Audience :: Science/Research
Classifier: Topic :: Scientific/Engineering
Requires-Python: >=3.9
License-File: LICENSE
Requires-Dist: numpy >=1.20
Requires-Dist: scipy
Requires-Dist: numexpr >=2.7
Requires-Dist: matplotlib
Requires-Dist: astropy
